{"name":"Change language from English to French","id":"language-change-in-smt-application;change-language-from-english-to-french","testSteps":[{"number":1,"description":"Given User is on home page of SMT application","duration":10151,"startTime":"2023-01-31T10:23:49.059+05:30[Asia/Calcutta]","result":"SUCCESS","precondition":false,"level":0},{"number":2,"description":"And User is able to see login button on home page","duration":272,"startTime":"2023-01-31T10:23:59.215+05:30[Asia/Calcutta]","result":"SUCCESS","precondition":false,"level":0,"children":[{"number":3,"description":"Validate login button on home page","duration":251,"startTime":"2023-01-31T10:23:59.236+05:30[Asia/Calcutta]","result":"SUCCESS","precondition":false,"level":1}]},{"number":4,"description":"When User select \"French\" from language dropdown","duration":380,"startTime":"2023-01-31T10:23:59.487+05:30[Asia/Calcutta]","result":"SUCCESS","precondition":false,"level":0,"children":[{"number":5,"description":"Change language: French","duration":373,"startTime":"2023-01-31T10:23:59.493+05:30[Asia/Calcutta]","result":"SUCCESS","precondition":false,"level":1}]},{"number":6,"description":"Then \"Accueilly\" is displayed on the home page","duration":9,"startTime":"2023-01-31T10:23:59.868+05:30[Asia/Calcutta]","result":"SUCCESS","precondition":false,"level":0,"children":[{"number":7,"description":"Validate home page text exists: Accueilly","duration":4,"startTime":"2023-01-31T10:23:59.871+05:30[Asia/Calcutta]","result":"SUCCESS","precondition":false,"level":1}]}],"userStory":{"id":"language-change-in-smt-application","storyName":"Language change in SMT application","displayName":"Language change in SMT application","path":"Generic/LanguageChange.feature","narrative":"  We will be using this feature file for Language change functionality validations in SMT application mentioning all possible scenarios.","type":"feature"},"featureTag":{"name":"Generic/Language change in SMT application","type":"feature","displayName":"Generic/Language change in SMT application"},"title":"Change language from English to French","description":"","backgroundTitle":"User open SMT application","backgroundDescription":"","tags":[{"name":"Generic","type":"capability","displayName":"Generic"},{"name":"Generic/Language change in SMT application","type":"feature","displayName":"Language change in SMT application"}],"startTime":"2023-01-31T10:23:48.887+05:30[Asia/Calcutta]","duration":10994,"projectKey":"","sessionId":"4997d744e3f511227611baa3da18121a","driver":"chrome","isManualTestingUpToDate":false,"manual":false,"testSource":"Cucumber","result":"SUCCESS"}