{"name":"Verify user is able to add details of temperature and alarm and save","id":"arrivals-tab-in-smt-application-for-store-operator-user;verify-user-is-able-to-add-details-of-temperature-and-alarm-and-save","testSteps":[{"number":1,"description":"Given User is on home page","duration":11999,"startTime":"2022-12-28T13:34:42.807680200+05:30[Asia/Calcutta]","result":"SUCCESS","precondition":false,"level":0},{"number":2,"description":"When User is getting correct title of home page","duration":242,"startTime":"2022-12-28T13:34:54.818601700+05:30[Asia/Calcutta]","result":"SUCCESS","precondition":false,"level":0,"children":[{"number":3,"description":"Validate home page","duration":86,"startTime":"2022-12-28T13:34:54.962811100+05:30[Asia/Calcutta]","result":"SUCCESS","precondition":false,"level":1}]},{"number":4,"description":"Then User click on login button","duration":506,"startTime":"2022-12-28T13:34:55.068279500+05:30[Asia/Calcutta]","result":"SUCCESS","precondition":false,"level":0,"children":[{"number":5,"description":"Click login button","duration":470,"startTime":"2022-12-28T13:34:55.098212100+05:30[Asia/Calcutta]","result":"SUCCESS","precondition":false,"level":1}]},{"number":6,"description":"When User click on Proceed To Login button in \"English\"","duration":2614,"startTime":"2022-12-28T13:34:55.576588400+05:30[Asia/Calcutta]","result":"SUCCESS","precondition":false,"level":0,"children":[{"number":7,"description":"Click proceed to login button: English","duration":2603,"startTime":"2022-12-28T13:34:55.578681800+05:30[Asia/Calcutta]","result":"SUCCESS","precondition":false,"level":1}]},{"number":8,"description":"Then User enter email","duration":441,"startTime":"2022-12-28T13:34:58.202033+05:30[Asia/Calcutta]","result":"SUCCESS","precondition":false,"level":0,"children":[{"number":9,"description":"Enter email","duration":421,"startTime":"2022-12-28T13:34:58.218474400+05:30[Asia/Calcutta]","result":"SUCCESS","precondition":false,"level":1}]},{"number":10,"description":"And User enter password","duration":215,"startTime":"2022-12-28T13:34:58.646783400+05:30[Asia/Calcutta]","result":"SUCCESS","precondition":false,"level":0,"children":[{"number":11,"description":"Enter password","duration":208,"startTime":"2022-12-28T13:34:58.651010700+05:30[Asia/Calcutta]","result":"SUCCESS","precondition":false,"level":1}]},{"number":12,"description":"When User click on sign in button","duration":10182,"startTime":"2022-12-28T13:34:58.867226+05:30[Asia/Calcutta]","result":"SUCCESS","precondition":false,"level":0,"children":[{"number":13,"description":"Click sign in button","duration":157,"startTime":"2022-12-28T13:34:58.876066+05:30[Asia/Calcutta]","result":"SUCCESS","precondition":false,"level":1}]},{"number":14,"description":"Given User click on \"Apply\" button","duration":3795,"startTime":"2022-12-28T13:35:09.052216700+05:30[Asia/Calcutta]","result":"SUCCESS","precondition":false,"level":0,"children":[{"number":15,"description":"Click on button: Apply","duration":3777,"startTime":"2022-12-28T13:35:09.061323200+05:30[Asia/Calcutta]","result":"SUCCESS","precondition":false,"level":1}]},{"number":16,"description":"And User click on \"Temp Logging\" tab","duration":2575,"startTime":"2022-12-28T13:35:12.850442700+05:30[Asia/Calcutta]","result":"SUCCESS","precondition":false,"level":0,"children":[{"number":17,"description":"Click on tab: Temp Logging","duration":2559,"startTime":"2022-12-28T13:35:12.861205900+05:30[Asia/Calcutta]","result":"SUCCESS","precondition":false,"level":1}]},{"number":18,"description":"Given User click on \"Edit Temperature\" button in templogging tab","duration":1715,"startTime":"2022-12-28T13:35:15.428538900+05:30[Asia/Calcutta]","result":"SUCCESS","precondition":false,"level":0,"children":[{"number":19,"description":"Click on edit temperature button: Edit Temperature","duration":1531,"startTime":"2022-12-28T13:35:15.608415200+05:30[Asia/Calcutta]","result":"SUCCESS","precondition":false,"level":1}]},{"number":20,"description":"And User enter \"valid\" temperature details in table","duration":16202,"startTime":"2022-12-28T13:35:17.146730400+05:30[Asia/Calcutta]","result":"SUCCESS","precondition":false,"level":0,"children":[{"number":21,"description":"Enter valid details in table","duration":16191,"startTime":"2022-12-28T13:35:17.151717800+05:30[Asia/Calcutta]","result":"SUCCESS","precondition":false,"level":1}]},{"number":22,"description":"When User click on \"Save Temperature\" button in templogging tab","duration":505,"startTime":"2022-12-28T13:35:33.351594900+05:30[Asia/Calcutta]","result":"SUCCESS","precondition":false,"level":0,"children":[{"number":23,"description":"Click on save temperature button: Save Temperature","duration":495,"startTime":"2022-12-28T13:35:33.357156+05:30[Asia/Calcutta]","result":"SUCCESS","precondition":false,"level":1}]},{"number":24,"description":"Then Temperature logging data is created successfully","duration":2578,"startTime":"2022-12-28T13:35:33.858509500+05:30[Asia/Calcutta]","result":"SUCCESS","precondition":false,"level":0,"children":[{"number":25,"description":"Created message displayed","duration":2567,"startTime":"2022-12-28T13:35:33.862132700+05:30[Asia/Calcutta]","result":"SUCCESS","precondition":false,"level":1}]},{"number":26,"description":"And User wait for \"10\" seconds","duration":10038,"startTime":"2022-12-28T13:35:36.439360900+05:30[Asia/Calcutta]","result":"SUCCESS","precondition":false,"level":0},{"number":27,"description":"Then New data is visible in table","duration":2356,"startTime":"2022-12-28T13:35:46.481440400+05:30[Asia/Calcutta]","result":"SUCCESS","precondition":false,"level":0,"children":[{"number":28,"description":"Validate details in table","duration":2337,"startTime":"2022-12-28T13:35:46.491575100+05:30[Asia/Calcutta]","result":"SUCCESS","precondition":false,"level":1}]}],"userStory":{"id":"arrivals-tab-in-smt-application-for-store-operator-user","storyName":"Arrivals tab in SMT application for Store Operator user","displayName":"Arrivals tab in SMT application for Store Operator user","path":"StoreOperator/TempLogging.feature","narrative":"  We will be using this feature file for Store Operator user using Arrivals functionality validations in SMT application mentioning all possible scenarios.","type":"feature"},"featureTag":{"name":"Store operator/Arrivals tab in SMT application for Store Operator user","type":"feature","displayName":"Store operator/Arrivals tab in SMT application for Store Operator user"},"title":"Verify user is able to add details of temperature and alarm and save","description":"","backgroundTitle":"User login to SMT application and navigate to Arrivals tab","backgroundDescription":"","tags":[{"name":"Store operator/Arrivals tab in SMT application for Store Operator user","type":"feature","displayName":"Arrivals tab in SMT application for Store Operator user"},{"name":"Store operator","type":"capability","displayName":"Store operator"}],"startTime":"2022-12-28T13:34:42.473895700+05:30[Asia/Calcutta]","duration":66365,"projectKey":"","sessionId":"9ab271bb8c0f82a99bdf4b8ffab0ba59","driver":"chrome","isManualTestingUpToDate":false,"manual":false,"testSource":"Cucumber","result":"SUCCESS"}